panelini/__init__.py
panelini/main.css
panelini/main.py
panelini/assets/content.jpg
panelini/assets/favicon.ico
panelini/assets/header.jpg
panelini/assets/panelinilogo.png
panelini-0.7.2.dist-info/METADATA
panelini-0.7.2.dist-info/WHEEL
panelini-0.7.2.dist-info/licenses/LICENSE
panelini-0.7.2.dist-info/RECORD
