Metadata-Version: 2.4
Name: panelini
Version: 0.7.2
Summary: Panelini is a user-friendly Python package designed to provide an out-of-the-box panel with a beautiful and responsive layout. It simplifies the creation of interactive dashboards by handling dynamic content seamlessly using Python Panel components. Whether you're building complex data visualizations or simple interactive interfaces, panelini offers an easy-to-use solution that enhances productivity and aesthetics.
Project-URL: Homepage, https://opensemanticworld.github.io/panelini/
Project-URL: Repository, https://github.com/opensemanticworld/panelini
Project-URL: Documentation, https://opensemanticworld.github.io/panelini/
Author-email: Andreas Räder <andreas.raeder@isc.fraunhofer.de>
License-File: LICENSE
Keywords: python
Classifier: Intended Audience :: Developers
Classifier: Programming Language :: Python
Classifier: Programming Language :: Python :: 3
Classifier: Programming Language :: Python :: 3.10
Classifier: Programming Language :: Python :: 3.11
Classifier: Programming Language :: Python :: 3.12
Classifier: Programming Language :: Python :: 3.13
Classifier: Topic :: Software Development :: Libraries :: Python Modules
Requires-Python: <4.0,>=3.10
Requires-Dist: panel>=1.7.1
Requires-Dist: param>=2.2.1
Requires-Dist: watchfiles>=1.1.0
